[{"kode":"911801","nama":"Agats"},{"kode":"911804","nama":"Akat"},{"kode":"911821","nama":"Aswi"},{"kode":"911802","nama":"Atsj"},{"kode":"911822","nama":"Awyu"},{"kode":"911818","nama":"Ayip"},{"kode":"911819","nama":"Betcbamu"},{"kode":"911814","nama":"Der Koumur"},{"kode":"911805","nama":"Fayit"},{"kode":"911813","nama":"Jetsy"},{"kode":"911811","nama":"Joerat"},{"kode":"911820","nama":"Joutu"},{"kode":"911809","nama":"Kolf Braza"},{"kode":"911815","nama":"Kopay"},{"kode":"911823","nama":"Koroway Buluanop"},{"kode":"911806","nama":"Pantai Kasuari"},{"kode":"911812","nama":"Pulau Tiga"},{"kode":"911816","nama":"Safan"},{"kode":"911803","nama":"Sawa Erma"},{"kode":"911817","nama":"Sirets"},{"kode":"911807","nama":"Suator"},{"kode":"911808","nama":"Suru-suru"},{"kode":"911810","nama":"Unir Sirau"}]